hadro/__init__.py
hadro/config.py
hadro/engine.py
hadro/schema.py
hadro/version.py
hadro-0.0.4.dist-info/LICENSE
hadro-0.0.4.dist-info/METADATA
hadro-0.0.4.dist-info/NOTICES
hadro-0.0.4.dist-info/WHEEL
hadro-0.0.4.dist-info/top_level.txt
hadro-0.0.4.dist-info/RECORD
