Metadata-Version: 2.1
Name: hadro
Version: 0.0.4
Summary: Storage Engine
Home-page: https://github.com/mabel-dev/hadrodb/
Author: @joocer
Author-email: justin.joyce@joocer.com
Maintainer: @joocer
License-File: LICENSE
License-File: NOTICES
Requires-Dist: ormsgpack
Requires-Dist: orso
